ws/ddns/__init__.py
ws/ddns/update.py
ws/ddns/web.py
ws/ddns/tests/__init__.py
ws.ddns-1.6.0.dist-info/METADATA
ws.ddns-1.6.0.dist-info/WHEEL
ws.ddns-1.6.0.dist-info/entry_points.txt
ws.ddns-1.6.0.dist-info/RECORD
