Metadata-Version: 2.1
Name: ws.ddns
Version: 1.6.0
Summary: Update DNS settings using the Schlundtech XML-Gateway
Project-URL: Repository, https://github.com/wosc/schlund-ddns
Author-email: Wolfgang Schnerring <wosc@wosc.de>
License:  BSD-3-Clause
Requires-Python: >=3.7
Requires-Dist: flask
Requires-Dist: gocept-logging
Requires-Dist: lxml
Requires-Dist: requests
Provides-Extra: test
Requires-Dist: pytest; extra == 'test'
Requires-Dist: pytest-cov; extra == 'test'
